pydefect_2d/__init__.py
pydefect_2d/conftest.py
pydefect_2d/cli/__init__.py
pydefect_2d/cli/main.py
pydefect_2d/cli/main_function.py
pydefect_2d/cli/main_function_test.py
pydefect_2d/cli/main_plot_json.py
pydefect_2d/cli/main_plot_json_test.py
pydefect_2d/cli/main_test.py
pydefect_2d/cli/main_util.py
pydefect_2d/cli/main_util_function.py
pydefect_2d/cli/main_util_function_test.py
pydefect_2d/cli/main_util_test.py
pydefect_2d/correction/__init__.py
pydefect_2d/correction/correction_2d.py
pydefect_2d/correction/extrapolation_models.py
pydefect_2d/correction/extrapolation_models_test.py
pydefect_2d/correction/gauss_energy.py
pydefect_2d/correction/gauss_energy_test.py
pydefect_2d/correction/isolated_gauss.py
pydefect_2d/correction/isolated_gauss_test.py
pydefect_2d/correction/make_site_potential.py
pydefect_2d/correction/make_site_potential_test.py
pydefect_2d/dielectric/__init__.py
pydefect_2d/dielectric/dielectric_distribution.py
pydefect_2d/dielectric/dielectric_distribution_test.py
pydefect_2d/dielectric/distribution.py
pydefect_2d/dielectric/distribution_test.py
pydefect_2d/dielectric/make_extended_diele_dist.py
pydefect_2d/dielectric/make_extended_diele_dist_test.py
pydefect_2d/local_miscs/__init__.py
pydefect_2d/one_d/__init__.py
pydefect_2d/one_d/charge.py
pydefect_2d/one_d/potential.py
pydefect_2d/one_d/potential_test.py
pydefect_2d/one_d/slab_model.py
pydefect_2d/one_d/slab_model_test.py
pydefect_2d/three_d/__init__.py
pydefect_2d/three_d/grids.py
pydefect_2d/three_d/grids_test.py
pydefect_2d/three_d/slab_model.py
pydefect_2d/three_d/slab_model_plotter.py
pydefect_2d/three_d/slab_model_plotter_test.py
pydefect_2d/three_d/slab_model_test.py
pydefect_2d/util/__init__.py
pydefect_2d/util/atom_disp.py
pydefect_2d/util/atom_disp_test.py
pydefect_2d/util/utils.py
pydefect_2d/util/utils_test.py
pydefect_2d-0.1.3.dist-info/METADATA
pydefect_2d-0.1.3.dist-info/WHEEL
pydefect_2d-0.1.3.dist-info/entry_points.txt
pydefect_2d-0.1.3.dist-info/top_level.txt
pydefect_2d-0.1.3.dist-info/RECORD
